tefas_ui.py
tefas_ui-2022.10.27.dist-info/METADATA
tefas_ui-2022.10.27.dist-info/WHEEL
tefas_ui-2022.10.27.dist-info/entry_points.txt
tefas_ui-2022.10.27.dist-info/top_level.txt
tefas_ui-2022.10.27.dist-info/RECORD
