Metadata-Version: 2.1
Name: tefas-ui
Version: 2022.10.27
Requires-Dist: rich (>=11.0.0)
Requires-Dist: tefas-crawler (==0.3.3)
Provides-Extra: forex
Requires-Dist: forex-python (>=1.8) ; extra == 'forex'
